froster/__init__.py
froster/froster.py
froster-0.22.0.dist-info/METADATA
froster-0.22.0.dist-info/WHEEL
froster-0.22.0.dist-info/entry_points.txt
froster-0.22.0.dist-info/licenses/LICENSE
froster-0.22.0.dist-info/RECORD
