Metadata-Version: 2.4
Name: froster
Version: 0.22.0
Summary: Froster is a tool for easy archive and restore between local file systems and AWS S3 storage.
License: MIT
License-File: LICENSE
Author: Dirk Petersen
Author-email: no@mail.com
Requires-Python: >=3.10,<4.0
Classifier: License :: OSI Approved :: MIT License
Classifier: Programming Language :: Python :: 3
Classifier: Programming Language :: Python :: 3.10
Classifier: Programming Language :: Python :: 3.11
Classifier: Programming Language :: Python :: 3.12
Classifier: Programming Language :: Python :: 3.13
Classifier: Programming Language :: Python :: 3.14
Requires-Dist: boto3 (>=1.40.55,<2.0.0)
Requires-Dist: duckdb (>=1.4.1,<2.0.0)
Requires-Dist: inquirer (>=3.4.1,<4.0.0)
Requires-Dist: psutil (>=7.1.1,<8.0.0)
Requires-Dist: requests (>=2.32.5,<3.0.0)
Requires-Dist: setuptools (>=75.8.0,<76.0.0)
Requires-Dist: textual (>=6.3.0,<7.0.0)
Requires-Dist: tqdm (>=4.67.1,<5.0.0)
Requires-Dist: visidata (>=3.1.1,<4.0.0)
